easyqiwi/__init__.py
easyqiwi/easyqiwi.py
easyqiwi-1.0.2.dist-info/LICENSE
easyqiwi-1.0.2.dist-info/METADATA
easyqiwi-1.0.2.dist-info/WHEEL
easyqiwi-1.0.2.dist-info/top_level.txt
easyqiwi-1.0.2.dist-info/RECORD
