Metadata-Version: 2.1
Name: easyqiwi
Version: 1.0.2
Summary: Асинхронный Python модуль для работы с QIWI API.
Home-page: https://github.com/DedInc/easyqiwi
Author: Maehdakvan
Author-email: visitanimation@google.com
Project-URL: Bug Tracker, https://github.com/DedInc/easyqiwi/issues
Classifier: Programming Language :: Python :: 3
Classifier: License :: OSI Approved :: MIT License
Classifier: Operating System :: OS Independent
Requires-Python: >=3.6
License-File: LICENSE
Requires-Dist: asyncio
Requires-Dist: httpx
Requires-Dist: httpx-socks
Requires-Dist: httpx-socks[asyncio]
Requires-Dist: httpx-socks[trio]
